whisperx_fix/SubtitlesProcessor.py
whisperx_fix/__init__.py
whisperx_fix/__main__.py
whisperx_fix/alignment.py
whisperx_fix/asr.py
whisperx_fix/asr_copy.py
whisperx_fix/audio.py
whisperx_fix/conjunctions.py
whisperx_fix/diarize.py
whisperx_fix/transcribe.py
whisperx_fix/types.py
whisperx_fix/utils.py
whisperx_fix/assets/mel_filters.npz
whisperx_fix/assets/pytorch_model.bin
whisperx_fix/vads/__init__.py
whisperx_fix/vads/pyannote.py
whisperx_fix/vads/silero.py
whisperx_fix/vads/vad.py
whisperx_fix-0.0.2.dist-info/licenses/LICENSE
whisperx_fix-0.0.2.dist-info/METADATA
whisperx_fix-0.0.2.dist-info/WHEEL
whisperx_fix-0.0.2.dist-info/entry_points.txt
whisperx_fix-0.0.2.dist-info/top_level.txt
whisperx_fix-0.0.2.dist-info/RECORD
