Metadata-Version: 2.4
Name: whisperx_fix
Version: 0.0.2
Summary: Time-Accurate Automatic Speech Recognition using Whisper.
Author: Max Bain
License: BSD-2-Clause
Project-URL: repository, https://github.com/m-bain/whisperx
Requires-Python: <3.13,>=3.9
License-File: LICENSE
Requires-Dist: ctranslate2>=4.5.0
Requires-Dist: faster-whisper>=1.1.1
Requires-Dist: nltk>=3.9.1
Requires-Dist: numpy>=2.0.2
Requires-Dist: onnxruntime>=1.19
Requires-Dist: pandas>=2.2.3
Requires-Dist: pyannote-audio>=3.3.2
Requires-Dist: torch>=2.5.1
Requires-Dist: torchaudio>=2.5.1
Requires-Dist: transformers>=4.48.0
Dynamic: license-file
